groupme/__init__.py
groupme/attachments.py
groupme/bot.py
groupme_wrapper-0.1.1.dist-info/licenses/LICENSE.txt
groupme_wrapper-0.1.1.dist-info/METADATA
groupme_wrapper-0.1.1.dist-info/WHEEL
groupme_wrapper-0.1.1.dist-info/top_level.txt
groupme_wrapper-0.1.1.dist-info/RECORD
