Metadata-Version: 2.4
Name: groupme-wrapper
Version: 0.1.1
Summary: A Python wrapper for the GroupMe API
Home-page: https://github.com/cmajorix/groupme
Author: Lily Groth
Author-email: groth@u.northwestern.edu
Classifier: Programming Language :: Python :: 3
Classifier: License :: OSI Approved :: MIT License
Classifier: Operating System :: OS Independent
Requires-Python: >=3.6
License-File: LICENSE.txt
Requires-Dist: requests
Dynamic: author
Dynamic: author-email
Dynamic: classifier
Dynamic: description
Dynamic: description-content-type
Dynamic: home-page
Dynamic: license-file
Dynamic: requires-dist
Dynamic: requires-python
Dynamic: summary
